Metadata-Version: 2.1
Name: gitkeep2
Version: 1.0.0.post1
Summary: A tiny utility to force empty directories into a Git repo.
Home-page: https://github.com/mig82/py-gitkeep
Author: Miguelangel Fernandez
Author-email: miguelangelxfm@gmail.com
License: UNKNOWN
Platform: UNKNOWN
Classifier: Development Status :: 5 - Production/Stable
Classifier: Environment :: Console
Classifier: Intended Audience :: Developers
Classifier: Programming Language :: Python :: 3.7
Classifier: Topic :: Software Development :: Version Control :: Git
Classifier: Topic :: Utilities
